setup.py
bioinformatics_mill_models/__init__.py
bioinformatics_mill_models/models.py
bioinformatics_mill_models/settings.py
bioinformatics_mill_models/urls.py
bioinformatics_mill_models/wsgi.py
bioinformatics_mill_models.egg-info/PKG-INFO
bioinformatics_mill_models.egg-info/SOURCES.txt
bioinformatics_mill_models.egg-info/dependency_links.txt
bioinformatics_mill_models.egg-info/top_level.txt
bioinformatics_mill_models/migrations/0001_initial.py
bioinformatics_mill_models/migrations/__init__.py