Metadata-Version: 1.1
Name: bioinformatics-mill-models
Version: 0.1.1
Summary: An abstracted database model for the Bioinformatics Mill project
Home-page: https://www.greenelab.com
Author: Kurt Wheeler
Author-email: kurt.wheeler91@gmail.com
License: BSD License
Platform: UNKNOWN
Classifier: Environment :: Web Environment
Classifier: Framework :: Django
Classifier: Intended Audience :: Developers
Classifier: License :: OSI Approved :: BSD License
Classifier: Operating System :: OS Independent
Classifier: Programming Language :: Python
Classifier: Programming Language :: Python :: 3
Classifier: Programming Language :: Python :: 3.4
Classifier: Programming Language :: Python :: 3.5
Classifier: Topic :: Internet :: WWW/HTTP
